binakeExcel/__init__.py
binakeExcel/example.py
binakeexcel-1.6.4.dist-info/licenses/LICENSE.txt
binakeexcel-1.6.4.dist-info/METADATA
binakeexcel-1.6.4.dist-info/WHEEL
binakeexcel-1.6.4.dist-info/top_level.txt
binakeexcel-1.6.4.dist-info/RECORD
